recap/__init__.py
recap/_version.py
recap/exceptions.py
recap/adapter/__init__.py
recap/adapter/local.py
recap/client/__init__.py
recap/client/base_client.py
recap/db/__init__.py
recap/db/attribute.py
recap/db/base.py
recap/db/campaign.py
recap/db/exceptions.py
recap/db/process.py
recap/db/resource.py
recap/db/step.py
recap/db/migrations/README
recap/db/migrations/__init__.py
recap/db/migrations/add_sentinel.py
recap/db/migrations/env.py
recap/db/migrations/script.py.mako
recap/db/migrations/versions/1f61d287e423_initial_schema.py
recap/dsl/attribute_builder.py
recap/dsl/process_builder.py
recap/dsl/query.py
recap/dsl/resource_builder.py
recap/schemas/attribute.py
recap/schemas/common.py
recap/schemas/experiment.py
recap/schemas/process.py
recap/schemas/resource.py
recap/schemas/step.py
recap/tests/__init__.py
recap/tests/conftest.py
recap/tests/test_actions.py
recap/tests/test_attribute_value.py
recap/tests/test_builders_idempotent.py
recap/tests/test_builders_models.py
recap/tests/test_client.py
recap/tests/test_container.py
recap/tests/test_db_models.py
recap/tests/test_experiment.py
recap/tests/test_fragment_screening.py
recap/tests/test_fragment_screening_api.py
recap/tests/test_platemate_client.py
recap/tests/test_platemate_parity.py
recap/tests/test_process_assignment.py
recap/tests/test_process_run_update.py
recap/tests/test_query_dsl.py
recap/tests/test_schemas.py
recap/tests/test_template_guards.py
recap/tests/lix/test_api_soln_scattering.py
recap/tests/lix/test_solution_scattering.py
recap/tests/test_data/example.yml
recap/tests/test_data/lix_containers.yml
recap/tests/test_data/lix_experiment.yml
recap/utils/database.py
recap/utils/dsl.py
recap/utils/general.py
recap/utils/migrations.py
pyrecap-0.0.1a5.dist-info/METADATA
pyrecap-0.0.1a5.dist-info/WHEEL
pyrecap-0.0.1a5.dist-info/licenses/AUTHORS.rst
pyrecap-0.0.1a5.dist-info/licenses/LICENSE
pyrecap-0.0.1a5.dist-info/licenses/LICENSE_README
pyrecap-0.0.1a5.dist-info/RECORD
