Metadata-Version: 2.4
Name: pyrecap
Version: 0.0.1a5
Summary: Scientific framework for Reproducible Experiment Capture and Provenance
Project-URL: Homepage, https://github.com/NSLS2/recap
Project-URL: Documentation, https://github.com/NSLS2/recap
Project-URL: Repository, https://github.com/NSLS2/recap.git
Project-URL: Issues, https://github.com/NSLS2/recap/issues
Author-email: Venkateswaran Shekar <vshekar1@bnl.gov>
License: BSD-3-Clause
License-File: AUTHORS.rst
License-File: LICENSE
License-File: LICENSE_README
Keywords: experiments,provenance,reproducibility
Classifier: Development Status :: 3 - Alpha
Classifier: License :: OSI Approved :: BSD License
Classifier: Operating System :: OS Independent
Classifier: Programming Language :: Python :: 3
Classifier: Programming Language :: Python :: 3.10
Classifier: Programming Language :: Python :: 3.11
Classifier: Programming Language :: Python :: 3.12
Classifier: Programming Language :: Python :: 3.13
Requires-Python: >=3.10
Requires-Dist: pydantic>=2.0
Requires-Dist: python-slugify
Requires-Dist: sqlalchemy>=2.0
Provides-Extra: dev
Requires-Dist: pytest; extra == 'dev'
